{
    "key": "group_5f115507df754",
    "title": "General",
    "fields": [
        {
            "key": "field_605564571decd",
            "label": "Social media",
            "name": "",
            "type": "tab",
            "instructions": "",
            "required": 0,
            "conditional_logic": 0,
            "wrapper": {
                "width": "",
                "class": "",
                "id": ""
            },
            "placement": "left",
            "endpoint": 0
        },
        {
            "key": "field_60409136e9024",
            "label": "Linkedin",
            "name": "so_li",
            "type": "url",
            "instructions": "",
            "required": 0,
            "conditional_logic": 0,
            "wrapper": {
                "width": "",
                "class": "",
                "id": ""
            },
            "default_value": "",
            "placeholder": ""
        },
        {
            "key": "field_6055640657604",
            "label": "Twitter",
            "name": "so_tt",
            "type": "url",
            "instructions": "",
            "required": 0,
            "conditional_logic": 0,
            "wrapper": {
                "width": "",
                "class": "",
                "id": ""
            },
            "default_value": "",
            "placeholder": ""
        },
        {
            "key": "field_5f11550f18da1",
            "label": "Facebook",
            "name": "so_fb",
            "type": "url",
            "instructions": "",
            "required": 0,
            "conditional_logic": 0,
            "wrapper": {
                "width": "",
                "class": "",
                "id": ""
            },
            "default_value": "",
            "placeholder": ""
        },
        {
            "key": "field_5f11553018da2",
            "label": "Instagram",
            "name": "so_ig",
            "type": "url",
            "instructions": "",
            "required": 0,
            "conditional_logic": 0,
            "wrapper": {
                "width": "",
                "class": "",
                "id": ""
            },
            "default_value": "",
            "placeholder": ""
        },
        {
            "key": "field_60556424a7cb3",
            "label": "Copyright",
            "name": "copyright",
            "type": "text",
            "instructions": "",
            "required": 0,
            "conditional_logic": 0,
            "wrapper": {
                "width": "",
                "class": "",
                "id": ""
            },
            "default_value": "",
            "placeholder": "",
            "prepend": "",
            "append": "",
            "maxlength": ""
        },
        {
            "key": "field_605564e9d1152",
            "label": "Site message",
            "name": "",
            "type": "tab",
            "instructions": "",
            "required": 0,
            "conditional_logic": 0,
            "wrapper": {
                "width": "",
                "class": "",
                "id": ""
            },
            "placement": "left",
            "endpoint": 0
        },
        {
            "key": "field_605564f9d1153",
            "label": "Enable",
            "name": "site_enabled",
            "type": "true_false",
            "instructions": "",
            "required": 0,
            "conditional_logic": 0,
            "wrapper": {
                "width": "",
                "class": "",
                "id": ""
            },
            "message": "",
            "default_value": 0,
            "ui": 0,
            "ui_on_text": "",
            "ui_off_text": ""
        },
        {
            "key": "field_60556505d1154",
            "label": "Text",
            "name": "site_text",
            "type": "text",
            "instructions": "",
            "required": 0,
            "conditional_logic": 0,
            "wrapper": {
                "width": "",
                "class": "",
                "id": ""
            },
            "default_value": "",
            "placeholder": "",
            "prepend": "",
            "append": "",
            "maxlength": ""
        },
        {
            "key": "field_6055651fd1156",
            "label": "Button label",
            "name": "site_button_label",
            "type": "text",
            "instructions": "",
            "required": 0,
            "conditional_logic": 0,
            "wrapper": {
                "width": "50",
                "class": "",
                "id": ""
            },
            "default_value": "",
            "placeholder": "",
            "prepend": "",
            "append": "",
            "maxlength": ""
        },
        {
            "key": "field_6055650cd1155",
            "label": "Button link",
            "name": "site_button_link",
            "type": "page_link",
            "instructions": "",
            "required": 0,
            "conditional_logic": 0,
            "wrapper": {
                "width": "50",
                "class": "",
                "id": ""
            },
            "post_type": [
                "page",
                "post"
            ],
            "taxonomy": "",
            "allow_null": 1,
            "allow_archives": 0,
            "multiple": 0
        },
        {
            "key": "field_6056f462fa229",
            "label": "News",
            "name": "",
            "type": "tab",
            "instructions": "",
            "required": 0,
            "conditional_logic": 0,
            "wrapper": {
                "width": "",
                "class": "",
                "id": ""
            },
            "placement": "left",
            "endpoint": 0
        },
        {
            "key": "field_6056f46efa22a",
            "label": "Title",
            "name": "news_title",
            "type": "text",
            "instructions": "",
            "required": 0,
            "conditional_logic": 0,
            "wrapper": {
                "width": "",
                "class": "",
                "id": ""
            },
            "default_value": "",
            "placeholder": "",
            "prepend": "",
            "append": "",
            "maxlength": ""
        },
        {
            "key": "field_6056f476fa22b",
            "label": "Text",
            "name": "news_text",
            "type": "text",
            "instructions": "",
            "required": 0,
            "conditional_logic": 0,
            "wrapper": {
                "width": "",
                "class": "",
                "id": ""
            },
            "default_value": "",
            "placeholder": "",
            "prepend": "",
            "append": "",
            "maxlength": ""
        }
    ],
    "location": [
        [
            {
                "param": "options_page",
                "operator": "==",
                "value": "theme-general-settings"
            }
        ]
    ],
    "menu_order": 0,
    "position": "normal",
    "style": "default",
    "label_placement": "left",
    "instruction_placement": "label",
    "hide_on_screen": "",
    "active": true,
    "description": "",
    "modified": 1623660330
}